afterimage/__init__.py
afterimage/base_generator.py
afterimage-0.1.1.dist-info/METADATA
afterimage-0.1.1.dist-info/WHEEL
afterimage-0.1.1.dist-info/top_level.txt
afterimage-0.1.1.dist-info/RECORD
